ovos_skill_color_picker/LICENSE.md
ovos_skill_color_picker/MANIFEST.in
ovos_skill_color_picker/README.md
ovos_skill_color_picker/__init__.py
ovos_skill_color_picker/requirements.txt
ovos_skill_color_picker/version.py
ovos_skill_color_picker/gui/qt5/Title.qml
ovos_skill_color_picker/gui/qt5/single-color.qml
ovos_skill_color_picker/locale/ca/skill.json
ovos_skill_color_picker/locale/ca/dialog/color-not-found.dialog
ovos_skill_color_picker/locale/ca/dialog/report-color-by-hex-name-known.dialog
ovos_skill_color_picker/locale/ca/dialog/report-color-by-hex-name-not-known.dialog
ovos_skill_color_picker/locale/ca/dialog/report-color-by-name.dialog
ovos_skill_color_picker/locale/ca/dialog/report-color-by-rgb-name-known.dialog
ovos_skill_color_picker/locale/ca/dialog/report-color-by-rgb-name-not-known.dialog
ovos_skill_color_picker/locale/ca/intents/request-color-by-hex.intent
ovos_skill_color_picker/locale/ca/intents/request-color-by-name.intent
ovos_skill_color_picker/locale/ca/intents/request-color-by-rgb.intent
ovos_skill_color_picker/locale/ca/intents/request-color.intent
ovos_skill_color_picker/locale/da/skill.json
ovos_skill_color_picker/locale/da/dialog/color-not-found.dialog
ovos_skill_color_picker/locale/da/dialog/report-color-by-hex-name-known.dialog
ovos_skill_color_picker/locale/da/dialog/report-color-by-hex-name-not-known.dialog
ovos_skill_color_picker/locale/da/dialog/report-color-by-name.dialog
ovos_skill_color_picker/locale/da/dialog/report-color-by-rgb-name-known.dialog
ovos_skill_color_picker/locale/da/dialog/report-color-by-rgb-name-not-known.dialog
ovos_skill_color_picker/locale/da/intents/request-color-by-hex.intent
ovos_skill_color_picker/locale/da/intents/request-color-by-name.intent
ovos_skill_color_picker/locale/da/intents/request-color-by-rgb.intent
ovos_skill_color_picker/locale/da/intents/request-color.intent
ovos_skill_color_picker/locale/de/skill.json
ovos_skill_color_picker/locale/de/dialog/color-not-found.dialog
ovos_skill_color_picker/ovos_skill_color_picker.egg-info/PKG-INFO
ovos_skill_color_picker/ovos_skill_color_picker.egg-info/SOURCES.txt
ovos_skill_color_picker/ovos_skill_color_picker.egg-info/dependency_links.txt
ovos_skill_color_picker/ovos_skill_color_picker.egg-info/entry_points.txt
ovos_skill_color_picker/ovos_skill_color_picker.egg-info/requires.txt
ovos_skill_color_picker/ovos_skill_color_picker.egg-info/top_level.txt
ovos_skill_color_picker-0.0.7.dist-info/LICENSE.md
ovos_skill_color_picker-0.0.7.dist-info/METADATA
ovos_skill_color_picker-0.0.7.dist-info/WHEEL
ovos_skill_color_picker-0.0.7.dist-info/entry_points.txt
ovos_skill_color_picker-0.0.7.dist-info/top_level.txt
ovos_skill_color_picker-0.0.7.dist-info/RECORD
