Metadata-Version: 2.1
Name: ovos-skill-color-picker
Version: 0.0.7
Summary: ColorPickerSkill
Home-page: https://github.com/OpenVoiceOS/ovos-skill-color-picker
Author: krisgesling
Author-email: 
License: Apache2.0
Keywords: ovos skill plugin
License-File: LICENSE.md
Requires-Dist: ovos-workshop
Requires-Dist: ovos-color-parser
